{
    "relationships": [],
    "fields": [
        {
            "fieldId": 1,
            "fieldName": "name",
            "fieldType": "String"
        },
        {
            "fieldId": 2,
            "fieldName": "description",
            "fieldType": "String"
        },
        {
            "fieldId": 3,
            "fieldName": "cronExpression",
            "fieldType": "String"
        },
        {
            "fieldId": 4,
            "fieldName": "path",
            "fieldType": "String"
        }
    ],
    "changelogDate": "20160727151655",
    "dto": "no",
    "pagination": "pager"
}